{
  "id": "a16z:caviar",
  "a16z_company_id": "371731",
  "name": "Caviar",
  "slug": "caviar",
  "description": "Caviar is the easiest way for consumers and businesses to order food from favorite local eateries with the ability to live-track the order on a map. Browse a picture menu, place the order, and we'll deliver within 1 hour.\r\n\r\nCaviar offers restaurants a delivery solution in just a few minutes without any infrastructure, logistical, oroperational costs.",
  "website": "https://www.trycaviar.com/",
  "status": "exited",
  "sectors": [
    "consumer",
    "seed"
  ],
  "stages": [
    "seed"
  ],
  "source_urls": {
    "investment_list": "https://a16z.com/investment-list/",
    "portfolio": "https://a16z.com/portfolio/"
  },
  "source_evidence": {
    "in_investment_list": true,
    "in_portfolio": true
  },
  "first_seen_iso": "2026-02-18T06:50:52Z",
  "last_seen_iso": "2026-02-18T06:50:52Z"
}
