{
  "id": "a16z:lmarena",
  "a16z_company_id": "376972",
  "name": "LMArena",
  "slug": "lmarena",
  "description": null,
  "website": "https://lmarena.ai/",
  "status": "active",
  "sectors": [
    "infra"
  ],
  "stages": [],
  "source_urls": {
    "investment_list": "https://a16z.com/investment-list/",
    "portfolio": "https://a16z.com/portfolio/"
  },
  "source_evidence": {
    "in_investment_list": true,
    "in_portfolio": true
  },
  "first_seen_iso": "2026-02-25T06:51:39Z",
  "last_seen_iso": "2026-02-25T06:51:39Z"
}
