{
  "id": "a16z:maven",
  "a16z_company_id": "372298",
  "name": "Maven",
  "slug": "maven",
  "description": "Maven is a developer of an online cohort-based leadership program designed to create a community where anyone can start their own course.",
  "website": "https://maven.com/",
  "status": "active",
  "sectors": [
    "consumer",
    "seed"
  ],
  "stages": [
    "venture"
  ],
  "source_urls": {
    "investment_list": "https://a16z.com/investment-list/",
    "portfolio": "https://a16z.com/portfolio/"
  },
  "source_evidence": {
    "in_investment_list": true,
    "in_portfolio": true
  },
  "first_seen_iso": "2026-02-12T06:50:17Z",
  "last_seen_iso": "2026-02-12T06:50:17Z"
}
